paladin_mcp_server/__init__.py
paladin_mcp_server-0.1.0.dist-info/METADATA
paladin_mcp_server-0.1.0.dist-info/WHEEL
paladin_mcp_server-0.1.0.dist-info/entry_points.txt
paladin_mcp_server-0.1.0.dist-info/RECORD
