Metadata-Version: 2.4
Name: paladin-mcp-server
Version: 0.1.0
Summary: Add your description here
Author-email: Jianqi Wang <wangjianqi2009@gmail.com>
Requires-Python: >=3.13
Requires-Dist: mcp[cli]>=1.10.1
